[
  {
    "model": "sessions.session",
    "pk": "f9eg3jg84b33pzrzexy0zbekntgngw0s",
    "fields": {
      "session_data": ".eJxVjEEOwiAQRe_C2hAcCAWX7j0DmRlAqgaS0q6Md7ckXej2vff_WwTc1hK2npYwR3ERIE6_jJCfqQ4RH1jvTXKr6zKTHIk8bJe3FtPrerR_BwV72deobARmCw4AVJ4AJn_eATkCBZydIW8jR0bjPGfDNDqNXju2pLT4fAHaQje5:1pq2XM:eeQYAf96iU0_W2BgLJuYCjnWtQM6cEv5KmUzDQqDjqE",
      "expire_date": "2023-05-06T01:59:40.569Z"
    }
  },
  {
    "model": "board.user",
    "fields": {
      "password": "pbkdf2_sha256$320000$UpM9bR0KoXqjZOPmX54Fsp$hgDXXy6MLmkSzQlYPulAXf+NMPAfasWsuWtp/Ve64GU=",
      "last_login": "2023-04-22T01:58:02.286Z",
      "is_superuser": true,
      "username": "admin",
      "first_name": "",
      "last_name": "",
      "email": "admin@admin.com",
      "is_staff": true,
      "is_active": true,
      "date_joined": "2023-04-22T01:25:12.909Z",
      "type": "",
      "agency_name": "",
      "groups": [],
      "user_permissions": []
    }
  },
  {
    "model": "board.user",
    "fields": {
      "password": "pbkdf2_sha256$320000$Nct56Qwp7b3hmHbEXW2I1R$RkswOHQ0mblHzFlFSdJKTEUxvR9QRWXurUeIlmG3mX8=",
      "last_login": "2023-04-22T01:59:40.544Z",
      "is_superuser": false,
      "username": "contractor",
      "first_name": "",
      "last_name": "",
      "email": "contract@gmail.com",
      "is_staff": false,
      "is_active": true,
      "date_joined": "2023-04-22T01:28:27.306Z",
      "type": "CONTRACTOR",
      "agency_name": "Contractor R Us",
      "groups": [],
      "user_permissions": []
    }
  },
  {
    "model": "board.user",
    "fields": {
      "password": "pbkdf2_sha256$320000$bzJmRnkNoCaWGNyAj5tGJQ$aYs/ipPYcC66QsTDiE1X0fFIUWO28tAC+jaEIpkMJpQ=",
      "last_login": "2023-04-22T01:58:42.375Z",
      "is_superuser": false,
      "username": "contractee",
      "first_name": "",
      "last_name": "",
      "email": "hireu@yahoo.com",
      "is_staff": false,
      "is_active": true,
      "date_joined": "2023-04-22T01:29:17.913Z",
      "type": "CONTRACTEE",
      "agency_name": "Big Company",
      "groups": [],
      "user_permissions": []
    }
  },
  {
    "model": "board.user",
    "fields": {
      "password": "pbkdf2_sha256$320000$gZcHSTqZ1C2cIJ5bEGb6zX$etR2be/DlCmuTl02Ap4PBBY0yx+BBZg4l6Ahr6EKwY8=",
      "last_login": "2023-04-22T01:48:40.399Z",
      "is_superuser": false,
      "username": "contractor2",
      "first_name": "",
      "last_name": "",
      "email": "example@fake.com",
      "is_staff": false,
      "is_active": true,
      "date_joined": "2023-04-22T01:30:12.361Z",
      "type": "CONTRACTOR",
      "agency_name": "The Builders",
      "groups": [],
      "user_permissions": []
    }
  },
  {
    "model": "board.user",
    "fields": {
      "password": "pbkdf2_sha256$320000$RxQyRGuNB2uphgHzcKENyq$Vs7B2zt2WM+4Z51eb9BT9FQYWgCXtJy+pYsI8M1Ilrs=",
      "last_login": "2023-04-22T01:50:12.600Z",
      "is_superuser": false,
      "username": "contractor3",
      "first_name": "",
      "last_name": "",
      "email": "hello@ymail.com",
      "is_staff": false,
      "is_active": true,
      "date_joined": "2023-04-22T01:31:02.226Z",
      "type": "CONTRACTOR",
      "agency_name": "Roofs And Stuff",
      "groups": [],
      "user_permissions": []
    }
  },
  {
    "model": "board.user",
    "fields": {
      "password": "pbkdf2_sha256$320000$N4QUeRizJ3kmXElzuF1LDn$cq53KKwMlocQEHwd7JeOFeYoBYGV3bC1rA2eg0EY/Fc=",
      "last_login": "2023-04-22T01:41:49.325Z",
      "is_superuser": false,
      "username": "contractee2",
      "first_name": "",
      "last_name": "",
      "email": "data@whatever.net",
      "is_staff": false,
      "is_active": true,
      "date_joined": "2023-04-22T01:31:32.613Z",
      "type": "CONTRACTEE",
      "agency_name": "The Government",
      "groups": [],
      "user_permissions": []
    }
  },
  {
    "model": "board.user",
    "fields": {
      "password": "pbkdf2_sha256$320000$sYKNUvBmzh4x3cg3trznY1$9Ydnyu/FK4tR/Ack/nsagpf+NII0/+A/8P2Jn1Vtf8s=",
      "last_login": "2023-04-22T01:43:42.559Z",
      "is_superuser": false,
      "username": "contractee3",
      "first_name": "",
      "last_name": "",
      "email": "corp@aol.com",
      "is_staff": false,
      "is_active": true,
      "date_joined": "2023-04-22T01:32:14.568Z",
      "type": "CONTRACTEE",
      "agency_name": "Big Corp",
      "groups": [],
      "user_permissions": []
    }
  },
  {
    "model": "board.contract",
    "pk": 1,
    "fields": {
      "contract_title": "Build a Bridge",
      "bidding_end_date": "2022-11-11",
      "job_description": "Build us a nice bridge.  Not too tall please.",
      "contractee": ["contractee"],
      "date_placed": "2023-04-22T01:35:08.757Z",
      "closed": true
    }
  },
  {
    "model": "board.contract",
    "pk": 2,
    "fields": {
      "contract_title": "Parking Lots",
      "bidding_end_date": "2022-07-13",
      "job_description": "We need a really big parking lot and a few smaller ones.",
      "contractee": ["contractee"],
      "date_placed": "2023-04-22T01:35:51.315Z",
      "closed": false
    }
  },
  {
    "model": "board.contract",
    "pk": 3,
    "fields": {
      "contract_title": "Brick Building",
      "bidding_end_date": "2024-10-20",
      "job_description": "We need a really nice red brick building to store our stuff.",
      "contractee": ["contractee"],
      "date_placed": "2023-04-22T01:40:05.099Z",
      "closed": false
    }
  },
  {
    "model": "board.contract",
    "pk": 4,
    "fields": {
      "contract_title": "Build a Moat",
      "bidding_end_date": "2024-01-01",
      "job_description": "Crime has gotten out of hand.  We want to surround ourselves with a moat for protection.",
      "contractee": ["contractee"],
      "date_placed": "2023-04-22T01:40:55.489Z",
      "closed": false
    }
  },
  {
    "model": "board.contract",
    "pk": 5,
    "fields": {
      "contract_title": "We need a dock",
      "bidding_end_date": "2025-03-18",
      "job_description": "I want to buy a sail boat and need a place to park it.",
      "contractee": ["contractee2"],
      "date_placed": "2023-04-22T01:42:23.125Z",
      "closed": false
    }
  },
  {
    "model": "board.contract",
    "pk": 6,
    "fields": {
      "contract_title": "Remove some trees",
      "bidding_end_date": "2022-09-15",
      "job_description": "We need some trees gone ASAP",
      "contractee": ["contractee2"],
      "date_placed": "2023-04-22T01:43:13.999Z",
      "closed": false
    }
  },
  {
    "model": "board.contract",
    "pk": 7,
    "fields": {
      "contract_title": "Build a rail",
      "bidding_end_date": "2022-12-12",
      "job_description": "We want to allow a train to come directly to our business for shipping stuff to places.",
      "contractee": ["contractee3"],
      "date_placed": "2023-04-22T01:44:21.053Z",
      "closed": false
    }
  },
  {
    "model": "board.contract",
    "pk": 8,
    "fields": {
      "contract_title": "Build a nice path",
      "bidding_end_date": "2025-03-04",
      "job_description": "We want a path through the forest by us for hiking.",
      "contractee": ["contractee3"],
      "date_placed": "2023-04-22T01:44:59.190Z",
      "closed": false
    }
  },
  {
    "model": "board.bid",
    "pk": 1,
    "fields": {
      "amount": 18.55,
      "date_placed": "2023-04-22",
      "contract": 1,
      "contractor": ["contractor"],
      "accepted": true
    }
  },
  {
    "model": "board.bid",
    "pk": 2,
    "fields": {
      "amount": 1800.99,
      "date_placed": "2023-04-22",
      "contract": 3,
      "contractor": ["contractor"],
      "accepted": false
    }
  },
  {
    "model": "board.bid",
    "pk": 3,
    "fields": {
      "amount": 56000.86,
      "date_placed": "2023-04-22",
      "contract": 5,
      "contractor": ["contractor"],
      "accepted": false
    }
  },
  {
    "model": "board.bid",
    "pk": 4,
    "fields": {
      "amount": 1300.99,
      "date_placed": "2023-04-22",
      "contract": 4,
      "contractor": ["contractor"],
      "accepted": false
    }
  },
  {
    "model": "board.bid",
    "pk": 5,
    "fields": {
      "amount": 100000.98,
      "date_placed": "2023-04-22",
      "contract": 7,
      "contractor": ["contractor"],
      "accepted": false
    }
  },
  {
    "model": "board.bid",
    "pk": 6,
    "fields": {
      "amount": 16.99,
      "date_placed": "2023-04-22",
      "contract": 1,
      "contractor": ["contractor2"],
      "accepted": false
    }
  },
  {
    "model": "board.bid",
    "pk": 7,
    "fields": {
      "amount": 88888.88,
      "date_placed": "2023-04-22",
      "contract": 2,
      "contractor": ["contractor2"],
      "accepted": false
    }
  },
  {
    "model": "board.bid",
    "pk": 8,
    "fields": {
      "amount": 99.99,
      "date_placed": "2023-04-22",
      "contract": 4,
      "contractor": ["contractor2"],
      "accepted": false
    }
  },
  {
    "model": "board.bid",
    "pk": 9,
    "fields": {
      "amount": 132.22,
      "date_placed": "2023-04-22",
      "contract": 6,
      "contractor": ["contractor2"],
      "accepted": false
    }
  },
  {
    "model": "board.bid",
    "pk": 10,
    "fields": {
      "amount": 17.85,
      "date_placed": "2023-04-22",
      "contract": 1,
      "contractor": ["contractor3"],
      "accepted": false
    }
  },
  {
    "model": "board.bid",
    "pk": 11,
    "fields": {
      "amount": 131.31,
      "date_placed": "2023-04-22",
      "contract": 6,
      "contractor": ["contractor3"],
      "accepted": false
    }
  },
  {
    "model": "board.bid",
    "pk": 12,
    "fields": {
      "amount": 98.98,
      "date_placed": "2023-04-22",
      "contract": 4,
      "contractor": ["contractor3"],
      "accepted": false
    }
  },
  {
    "model": "board.bid",
    "pk": 14,
    "fields": {
      "amount": 15050.05,
      "date_placed": "2023-04-22",
      "contract": 3,
      "contractor": ["contractor3"],
      "accepted": false
    }
  },
  {
    "model": "admin.logentry",
    "pk": 1,
    "fields": {
      "action_time": "2023-04-22T01:45:55.382Z",
      "user": ["admin"],
      "content_type": ["board", "contract"],
      "object_id": "4",
      "object_repr": "Contract object (4)",
      "action_flag": 2,
      "change_message": "[{\"changed\": {\"fields\": [\"Contract title\"]}}]"
    }
  },
  {
    "model": "admin.logentry",
    "pk": 2,
    "fields": {
      "action_time": "2023-04-22T01:53:39.357Z",
      "user": ["admin"],
      "content_type": ["board", "contract"],
      "object_id": "1",
      "object_repr": "Contract object (1)",
      "action_flag": 2,
      "change_message": "[{\"changed\": {\"fields\": [\"Bidding end date\"]}}]"
    }
  },
  {
    "model": "admin.logentry",
    "pk": 3,
    "fields": {
      "action_time": "2023-04-22T01:54:13.036Z",
      "user": ["admin"],
      "content_type": ["board", "contract"],
      "object_id": "2",
      "object_repr": "Contract object (2)",
      "action_flag": 2,
      "change_message": "[{\"changed\": {\"fields\": [\"Bidding end date\"]}}]"
    }
  },
  {
    "model": "admin.logentry",
    "pk": 4,
    "fields": {
      "action_time": "2023-04-22T01:54:29.582Z",
      "user": ["admin"],
      "content_type": ["board", "contract"],
      "object_id": "6",
      "object_repr": "Contract object (6)",
      "action_flag": 2,
      "change_message": "[{\"changed\": {\"fields\": [\"Bidding end date\"]}}]"
    }
  },
  {
    "model": "admin.logentry",
    "pk": 5,
    "fields": {
      "action_time": "2023-04-22T01:54:36.875Z",
      "user": ["admin"],
      "content_type": ["board", "contract"],
      "object_id": "4",
      "object_repr": "Contract object (4)",
      "action_flag": 2,
      "change_message": "[{\"changed\": {\"fields\": [\"Bidding end date\"]}}]"
    }
  },
  {
    "model": "admin.logentry",
    "pk": 6,
    "fields": {
      "action_time": "2023-04-22T01:54:49.556Z",
      "user": ["admin"],
      "content_type": ["board", "contract"],
      "object_id": "7",
      "object_repr": "Contract object (7)",
      "action_flag": 2,
      "change_message": "[{\"changed\": {\"fields\": [\"Bidding end date\"]}}]"
    }
  },
  {
    "model": "admin.logentry",
    "pk": 7,
    "fields": {
      "action_time": "2023-04-22T01:56:07.888Z",
      "user": ["admin"],
      "content_type": ["board", "contract"],
      "object_id": "4",
      "object_repr": "Contract object (4)",
      "action_flag": 2,
      "change_message": "[{\"changed\": {\"fields\": [\"Bidding end date\"]}}]"
    }
  },
  {
    "model": "admin.logentry",
    "pk": 8,
    "fields": {
      "action_time": "2023-04-22T01:56:14.238Z",
      "user": ["admin"],
      "content_type": ["board", "contract"],
      "object_id": "7",
      "object_repr": "Contract object (7)",
      "action_flag": 2,
      "change_message": "[{\"changed\": {\"fields\": [\"Bidding end date\"]}}]"
    }
  },
  {
    "model": "admin.logentry",
    "pk": 9,
    "fields": {
      "action_time": "2023-04-22T01:58:11.347Z",
      "user": ["admin"],
      "content_type": ["board", "contract"],
      "object_id": "7",
      "object_repr": "Contract object (7)",
      "action_flag": 2,
      "change_message": "[{\"changed\": {\"fields\": [\"Bidding end date\"]}}]"
    }
  },
  {
    "model": "admin.logentry",
    "pk": 10,
    "fields": {
      "action_time": "2023-04-22T01:58:16.820Z",
      "user": ["admin"],
      "content_type": ["board", "contract"],
      "object_id": "7",
      "object_repr": "Contract object (7)",
      "action_flag": 2,
      "change_message": "[{\"changed\": {\"fields\": [\"Bidding end date\"]}}]"
    }
  }
]
